galaxy/__init__.py
galaxy/py.typed
galaxy/config/__init__.py
galaxy/config/config_manage.py
galaxy/config/schema.py
galaxy/config/script.py
galaxy/config/templates.py
galaxy/config/sample/auth_conf.xml.sample
galaxy/config/sample/build_sites.yml.sample
galaxy/config/sample/container_resolvers.yml.sample
galaxy/config/sample/data_manager_conf.xml.sample
galaxy/config/sample/datatypes_conf.xml.sample
galaxy/config/sample/disposable_email_blocklist.conf.sample
galaxy/config/sample/environment_modules_mapping.yml.sample
galaxy/config/sample/error_report.yml.sample
galaxy/config/sample/file_sources_conf.yml.sample
galaxy/config/sample/galaxy.yml.sample
galaxy/config/sample/job_conf.sample.yml
galaxy/config/sample/job_conf.xml.sample_advanced
galaxy/config/sample/job_conf.xml.sample_basic
galaxy/config/sample/job_resource_params_conf.xml.sample
galaxy/config/sample/lmod_modules_mapping.yml.sample
galaxy/config/sample/local_conda_mapping.yml.sample
galaxy/config/sample/object_store_conf.sample.yml
galaxy/config/sample/object_store_conf.xml.sample
galaxy/config/sample/oidc_backends_config.xml.sample
galaxy/config/sample/oidc_config.xml.sample
galaxy/config/sample/reports.yml.sample
galaxy/config/sample/themes_conf.yml.sample
galaxy/config/sample/tool_conf.xml.sample
galaxy/config/sample/tool_data_table_conf.xml.sample
galaxy/config/sample/tool_destinations.yml.sample
galaxy/config/sample/tool_recommendations_overwrite.yml.sample
galaxy/config/sample/tool_shed.yml.sample
galaxy/config/sample/tool_sheds_conf.xml.sample
galaxy/config/sample/trs_servers_conf.yml.sample
galaxy/config/sample/user_preferences_extra_conf.yml.sample
galaxy/config/sample/workflow_resource_mapper_conf.yml.sample
galaxy/config/sample/workflow_resource_params_conf.xml.sample
galaxy/config/sample/workflow_schedulers_conf.xml.sample
galaxy/config/schemas/config_schema.yml
galaxy/config/schemas/job_config_schema.yml
galaxy/config/schemas/reports_config_schema.yml
galaxy_config-25.0.3.dist-info/licenses/LICENSE
galaxy_config-25.0.3.dist-info/METADATA
galaxy_config-25.0.3.dist-info/WHEEL
galaxy_config-25.0.3.dist-info/entry_points.txt
galaxy_config-25.0.3.dist-info/top_level.txt
galaxy_config-25.0.3.dist-info/RECORD
